<?xml version="1.0" encoding="utf-8" ?>
<dwsync>
<file name="contributing.txt" server="ftps20.us.cloudlogin.co" local="134176605949669487" remote="134049948000000000" Dst="2" />
<file name="functions.php" server="ftps20.us.cloudlogin.co" local="134176605950273834" remote="134049981600000000" Dst="2" />
<file name="package.json" server="ftps20.us.cloudlogin.co" local="134176605951849501" remote="134090538600000000" Dst="2" />
<file name="package-lock.json" server="ftps20.us.cloudlogin.co" local="134176605952115843" remote="134090538600000000" Dst="2" />
<file name="readme.txt" server="ftps20.us.cloudlogin.co" local="134176606045169852" remote="134090538600000000" Dst="2" />
<file name="style.css" server="ftps20.us.cloudlogin.co" local="134176606046426569" remote="134090538600000000" Dst="2" />
<file name="style.min.css" server="ftps20.us.cloudlogin.co" local="134176606046812316" remote="134049948000000000" Dst="2" />
<file name="screenshot.png" server="ftps20.us.cloudlogin.co" local="134176606048078742" remote="133727472000000000" Dst="2" />
<file name="theme.json" server="ftps20.us.cloudlogin.co" local="134176606085607469" remote="133851852000000000" Dst="2" />
</dwsync>