<?xml version="1.0" encoding="utf-8" ?>
<dwsync>
<file name="content-rtl.css" server="ftps20.us.cloudlogin.co" local="134176607168107950" remote="134085608400000000" Dst="2" />
<file name="content-rtl.min.css" server="ftps20.us.cloudlogin.co" local="134176607168596860" remote="134085608400000000" Dst="2" />
<file name="content.css" server="ftps20.us.cloudlogin.co" local="134176607169423117" remote="134085608400000000" Dst="2" />
<file name="content.min.css" server="ftps20.us.cloudlogin.co" local="134176607169890219" remote="134085608400000000" Dst="2" />
<file name="default-editor-styles-rtl.css" server="ftps20.us.cloudlogin.co" local="134176607170267199" remote="134055188400000000" Dst="2" />
<file name="default-editor-styles-rtl.min.css" server="ftps20.us.cloudlogin.co" local="134176607170883272" remote="134055188400000000" Dst="2" />
<file name="default-editor-styles.css" server="ftps20.us.cloudlogin.co" local="134176607171547175" remote="134055188400000000" Dst="2" />
<file name="default-editor-styles.min.css" server="ftps20.us.cloudlogin.co" local="134176607171577148" remote="134055188400000000" Dst="2" />
<file name="style-rtl.css" server="ftps20.us.cloudlogin.co" local="134176607173766897" remote="134142142200000000" Dst="2" />
<file name="style-rtl.min.css" server="ftps20.us.cloudlogin.co" local="134176607174325650" remote="134142142200000000" Dst="2" />
<file name="style.css" server="ftps20.us.cloudlogin.co" local="134176607175191606" remote="134142142200000000" Dst="2" />
<file name="style.min.css" server="ftps20.us.cloudlogin.co" local="134176607176644544" remote="134142142200000000" Dst="2" />
</dwsync>