<?xml version="1.0" encoding="utf-8" ?>
<dwsync>
<file name="admin-bar-rtl.css" server="ftps20.us.cloudlogin.co" local="134141187000000000" remote="134141187000000000" Dst="2" />
<file name="admin-bar-rtl.min.css" server="ftps20.us.cloudlogin.co" local="134141187000000000" remote="134141187000000000" Dst="2" />
<file name="admin-bar.css" server="ftps20.us.cloudlogin.co" local="134141187000000000" remote="134141187000000000" Dst="2" />
<file name="admin-bar.min.css" server="ftps20.us.cloudlogin.co" local="134141187000000000" remote="134141187000000000" Dst="2" />
<file name="buttons-rtl.css" server="ftps20.us.cloudlogin.co" local="133517484000000000" remote="133517484000000000" Dst="2" />
<file name="buttons-rtl.min.css" server="ftps20.us.cloudlogin.co" local="133517484000000000" remote="133517484000000000" Dst="2" />
<file name="buttons.css" server="ftps20.us.cloudlogin.co" local="133517484000000000" remote="133517484000000000" Dst="2" />
<file name="buttons.min.css" server="ftps20.us.cloudlogin.co" local="133517484000000000" remote="133517484000000000" Dst="2" />
<file name="classic-themes.css" server="ftps20.us.cloudlogin.co" local="133207308000000000" remote="133207308000000000" Dst="2" />
<file name="classic-themes.min.css" server="ftps20.us.cloudlogin.co" local="133207308000000000" remote="133207308000000000" Dst="2" />
<file name="customize-preview-rtl.css" server="ftps20.us.cloudlogin.co" local="132561036000000000" remote="132561036000000000" Dst="2" />
<file name="customize-preview-rtl.min.css" server="ftps20.us.cloudlogin.co" local="132592140000000000" remote="132592140000000000" Dst="2" />
<file name="customize-preview.css" server="ftps20.us.cloudlogin.co" local="132561036000000000" remote="132561036000000000" Dst="2" />
<file name="customize-preview.min.css" server="ftps20.us.cloudlogin.co" local="132592140000000000" remote="132592140000000000" Dst="2" />
<file name="dashicons.css" server="ftps20.us.cloudlogin.co" local="134084970000000000" remote="134084970000000000" Dst="2" />
<file name="dashicons.min.css" server="ftps20.us.cloudlogin.co" local="134084970000000000" remote="134084970000000000" Dst="2" />
<file name="editor-rtl.css" server="ftps20.us.cloudlogin.co" local="134141187000000000" remote="134141187000000000" Dst="2" />
<file name="editor-rtl.min.css" server="ftps20.us.cloudlogin.co" local="134141187000000000" remote="134141187000000000" Dst="2" />
<file name="editor.css" server="ftps20.us.cloudlogin.co" local="134141187000000000" remote="134141187000000000" Dst="2" />
<file name="editor.min.css" server="ftps20.us.cloudlogin.co" local="134141187000000000" remote="134141187000000000" Dst="2" />
<file name="jquery-ui-dialog-rtl.css" server="ftps20.us.cloudlogin.co" local="134141187000000000" remote="134141187000000000" Dst="2" />
<file name="jquery-ui-dialog-rtl.min.css" server="ftps20.us.cloudlogin.co" local="134141187000000000" remote="134141187000000000" Dst="2" />
<file name="jquery-ui-dialog.css" server="ftps20.us.cloudlogin.co" local="134141187000000000" remote="134141187000000000" Dst="2" />
<file name="jquery-ui-dialog.min.css" server="ftps20.us.cloudlogin.co" local="134141187000000000" remote="134141187000000000" Dst="2" />
<file name="media-views-rtl.css" server="ftps20.us.cloudlogin.co" local="134141187000000000" remote="134141187000000000" Dst="2" />
<file name="media-views-rtl.min.css" server="ftps20.us.cloudlogin.co" local="134141187000000000" remote="134141187000000000" Dst="2" />
<file name="media-views.css" server="ftps20.us.cloudlogin.co" local="134141187000000000" remote="134141187000000000" Dst="2" />
<file name="media-views.min.css" server="ftps20.us.cloudlogin.co" local="134141187000000000" remote="134141187000000000" Dst="2" />
<file name="wp-auth-check-rtl.css" server="ftps20.us.cloudlogin.co" local="134141187000000000" remote="134141187000000000" Dst="2" />
<file name="wp-auth-check-rtl.min.css" server="ftps20.us.cloudlogin.co" local="134141187000000000" remote="134141187000000000" Dst="2" />
<file name="wp-auth-check.css" server="ftps20.us.cloudlogin.co" local="134141187000000000" remote="134141187000000000" Dst="2" />
<file name="wp-auth-check.min.css" server="ftps20.us.cloudlogin.co" local="134141187000000000" remote="134141187000000000" Dst="2" />
<file name="wp-embed-template-ie.css" server="ftps20.us.cloudlogin.co" local="134050608000000000" remote="134050608000000000" Dst="2" />
<file name="wp-embed-template-ie.min.css" server="ftps20.us.cloudlogin.co" local="134050608000000000" remote="134050608000000000" Dst="2" />
<file name="wp-embed-template.css" server="ftps20.us.cloudlogin.co" local="133928784000000000" remote="133928784000000000" Dst="2" />
<file name="wp-embed-template.min.css" server="ftps20.us.cloudlogin.co" local="133928784000000000" remote="133928784000000000" Dst="2" />
<file name="wp-empty-template-alert.css" server="ftps20.us.cloudlogin.co" local="133767180000000000" remote="133767180000000000" Dst="2" />
<file name="wp-empty-template-alert.min.css" server="ftps20.us.cloudlogin.co" local="133767180000000000" remote="133767180000000000" Dst="2" />
<file name="wp-pointer-rtl.css" server="ftps20.us.cloudlogin.co" local="134141187000000000" remote="134141187000000000" Dst="2" />
<file name="wp-pointer-rtl.min.css" server="ftps20.us.cloudlogin.co" local="134141187000000000" remote="134141187000000000" Dst="2" />
<file name="wp-pointer.css" server="ftps20.us.cloudlogin.co" local="134141187000000000" remote="134141187000000000" Dst="2" />
<file name="wp-pointer.min.css" server="ftps20.us.cloudlogin.co" local="134141187000000000" remote="134141187000000000" Dst="2" />
</dwsync>